puput/__init__.py
puput/abstracts.py
puput/apps.py
puput/comments.py
puput/feeds.py
puput/fields.py
puput/managers.py
puput/models.py
puput/routes.py
puput/signals.py
puput/urls.py
puput/utils.py
puput/views.py
puput/wagtail_hooks.py
puput/widgets.py
puput/conf/__init__.py
puput/conf/defaults.py
puput/locale/ar/LC_MESSAGES/django.mo
puput/locale/ar/LC_MESSAGES/django.po
puput/locale/ca/LC_MESSAGES/django.mo
puput/locale/ca/LC_MESSAGES/django.po
puput/locale/de/LC_MESSAGES/django.mo
puput/locale/de/LC_MESSAGES/django.po
puput/locale/en/LC_MESSAGES/django.mo
puput/locale/en/LC_MESSAGES/django.po
puput/locale/es/LC_MESSAGES/django.mo
puput/locale/es/LC_MESSAGES/django.po
puput/locale/fr/LC_MESSAGES/django.mo
puput/locale/fr/LC_MESSAGES/django.po
puput/locale/it/LC_MESSAGES/django.mo
puput/locale/it/LC_MESSAGES/django.po
puput/locale/ja/LC_MESSAGES/django.mo
puput/locale/ja/LC_MESSAGES/django.po
puput/locale/nl/LC_MESSAGES/django.mo
puput/locale/nl/LC_MESSAGES/django.po
puput/locale/pl/LC_MESSAGES/django.mo
puput/locale/pl/LC_MESSAGES/django.po
puput/locale/pt_BR/LC_MESSAGES/django.mo
puput/locale/pt_BR/LC_MESSAGES/django.po
puput/locale/pt_PT/LC_MESSAGES/django.mo
puput/locale/pt_PT/LC_MESSAGES/django.po
puput/locale/ru/LC_MESSAGES/django.mo
puput/locale/ru/LC_MESSAGES/django.po
puput/management/__init__.py
puput/management/commands/__init__.py
puput/management/commands/puput_initial_data.py
puput/migrations/0001_initial.py
puput/migrations/0002_auto_20150919_0925.py
puput/migrations/0003_add_short_feed_description_to_blog_page.py
puput/migrations/0004_auto_20170912_0928.py
puput/migrations/0005_blogpage_main_color.py
puput/migrations/0006_entrypage_markdown_body.py
puput/migrations/0007_alter_entrypage_body.py
puput/migrations/0008_alter_tagentrypage_tag.py
puput/migrations/__init__.py
puput/static/colorful/arrow.gif
puput/static/colorful/colorPicker.css
puput/static/puput/css/bootstrap.min.css
puput/static/puput/css/font-awesome.min.css
puput-2.2.0.dist-info/AUTHORS
puput-2.2.0.dist-info/LICENSE
puput-2.2.0.dist-info/METADATA
puput-2.2.0.dist-info/WHEEL
puput-2.2.0.dist-info/top_level.txt
puput-2.2.0.dist-info/RECORD
