Metadata-Version: 2.1
Name: puput
Version: 2.2.0
Summary: A Django blog app implemented in Wagtail.
Home-page: http://github.com/APSL/puput
Author: Marc Tudurí
Author-email: marctc@gmail.com
Keywords: django wagtail puput blog cms app
Classifier: Environment :: Web Environment
Classifier: Framework :: Django
Classifier: Framework :: Django :: 4.2
Classifier: Framework :: Django :: 5.0
Classifier: Framework :: Wagtail
Classifier: Framework :: Wagtail :: 5
Classifier: Framework :: Wagtail :: 6
Classifier: Intended Audience :: Developers
Classifier: Programming Language :: Python
Classifier: Programming Language :: Python :: 3
Classifier: Programming Language :: Python :: 3.8
Classifier: Programming Language :: Python :: 3.9
Classifier: Programming Language :: Python :: 3.10
Classifier: Programming Language :: Python :: 3.11
Classifier: Programming Language :: Python :: 3.12
Classifier: Operating System :: OS Independent
Classifier: Topic :: Software Development
License-File: LICENSE
License-File: AUTHORS
Requires-Dist: wagtail<7.0,>=5.2
Requires-Dist: django-el-pagination==4.0.0
Requires-Dist: django-taggit<6.2,>=5.0
Requires-Dist: wagtail-markdown==0.11.1
